AutoCython/AutoCython.py
AutoCython/__init__.py
AutoCython/compile.py
AutoCython/run_tasks.py
AutoCython/tools.py
autocython_jianjun-2.1.0.dist-info/licenses/LICENSE
autocython_jianjun-2.1.0.dist-info/METADATA
autocython_jianjun-2.1.0.dist-info/WHEEL
autocython_jianjun-2.1.0.dist-info/entry_points.txt
autocython_jianjun-2.1.0.dist-info/top_level.txt
autocython_jianjun-2.1.0.dist-info/RECORD
