Metadata-Version: 2.4
Name: AutoCython-jianjun
Version: 2.1.0
Summary: 自动Cython，使用Cython批量编译.py文件为.pyd文件！
Author-email: jianjun <910667956@qq.com>
License: MIT License
Project-URL: homepage, https://github.com/EVA-JianJun/AutoCython
Project-URL: repository, https://github.com/EVA-JianJun/AutoCython
Project-URL: documentation, https://github.com/EVA-JianJun/AutoCython#readme
Keywords: cython,compile,pyd,pyc,python,autopyd
Classifier: Programming Language :: Python :: 3
Classifier: License :: OSI Approved :: MIT License
Classifier: Operating System :: OS Independent
License-File: LICENSE
Requires-Dist: setuptools
Requires-Dist: cython
Requires-Dist: rich
Dynamic: license-file
